juicydir/__init__.py
juicydir/juicydir.py
juicydir-1.0.7.dist-info/LICENSE
juicydir-1.0.7.dist-info/METADATA
juicydir-1.0.7.dist-info/WHEEL
juicydir-1.0.7.dist-info/entry_points.txt
juicydir-1.0.7.dist-info/top_level.txt
juicydir-1.0.7.dist-info/RECORD
