Metadata-Version: 2.1
Name: juicydir
Version: 1.0.7
Summary: Juicy Dir - Recursive File & Content Scanner
Home-page: https://github.com/TraxionRPh/juicydir
Author: Griffin Skaff
Author-email: griffts@comcast.net
Classifier: Programming Language :: Python :: 3
Classifier: License :: OSI Approved :: MIT License
Classifier: Operating System :: OS Independent
Requires-Python: >=3.6
License-File: LICENSE
Requires-Dist: PyYAML
